<?xml version="1.0" encoding="UTF-8"?>
<mappings xmlns="http://dozer.sourceforge.net"
          xmlns:xsi="http://www.w3.org/2001/XMLSchema-instance"
          xsi:schemaLocation="http://dozer.sourceforge.net
          http://dozer.sourceforge.net/schema/beanmapping.xsd">
  <mapping>
    <class-a>kz.kegoc.bln.entity.media.oper.TemplateMeteringReading</class-a>
    <class-b>kz.kegoc.bln.entity.media.oper.dto.TemplateMeteringReadingDto</class-b>

    <field>
      <a>docType.id</a>
      <b>docTypeId</b>
    </field>

    <field>
      <a>docType.name</a>
      <b>docTypeName</b>
    </field>

    <field>
      <a>group.id</a>
      <b>groupId</b>
    </field>

    <field>
      <a>group.name</a>
      <b>groupName</b>
    </field>
  </mapping>
</mappings> 